__init__.py
spotipie/__init__.py
spotipie/client.py
spotipie/exceptions.py
spotipie/utils.py
spotipie/auth/__init__.py
spotipie/auth/_token.py
spotipie/auth/events.py
spotipie/auth/sessions.py
spotipie/auth/utils.py
spotipie/auth/_app/__init__.py
spotipie/auth/_app/app.py
spotipie/auth/_app/static/style.css
spotipie/auth/_app/templates/access_denied.html
spotipie/auth/_app/templates/callback.html
spotipie/auth/_app/templates/error.html
spotipie/auth/_app/templates/layout.html
spotipie/auth/_app/templates/success.html
spotipie-0.1.2.dist-info/AUTHORS.rst
spotipie-0.1.2.dist-info/LICENSE
spotipie-0.1.2.dist-info/METADATA
spotipie-0.1.2.dist-info/WHEEL
spotipie-0.1.2.dist-info/top_level.txt
spotipie-0.1.2.dist-info/zip-safe
spotipie-0.1.2.dist-info/RECORD
