Metadata-Version: 2.1
Name: spotipie
Version: 0.1.2
Summary: Another client for the Spotify Web API
Home-page: https://github.com/janLuke/spotipie
Author: Gianluca Gippetto
Author-email: gianluca.gippetto@gmail.com
License: MIT license
Keywords: spotify,api,client
Platform: UNKNOWN
Classifier: Intended Audience :: Developers
Classifier: License :: OSI Approved :: MIT License
Classifier: Operating System :: Unix
Classifier: Operating System :: POSIX
Classifier: Operating System :: Microsoft :: Windows
Classifier: Programming Language :: Python
Classifier: Programming Language :: Python :: 3.5
Classifier: Programming Language :: Python :: 3.6
Classifier: Programming Language :: Python :: 3.7
Classifier: Programming Language :: Python :: 3.8
Classifier: Programming Language :: Python :: Implementation :: CPython
Requires-Dist: oauthlib
Requires-Dist: urllib3
Requires-Dist: requests
Requires-Dist: requests-oauthlib
Requires-Dist: cachecontrol
Requires-Dist: attrs
Provides-Extra: auth-app
Requires-Dist: flask ; extra == 'auth-app'
